extras/__init__.py
extras/multiply.py
karanonymous_pack-0.0.1.dist-info/METADATA
karanonymous_pack-0.0.1.dist-info/WHEEL
karanonymous_pack-0.0.1.dist-info/top_level.txt
karanonymous_pack-0.0.1.dist-info/RECORD
