Metadata-Version: 2.1
Name: karanonymous-pack
Version: 0.0.1
Summary: My first Python package
Home-page: UNKNOWN
Author: Karan Kapuria
Author-email: <kkapuria@labcorp.com>
License: UNKNOWN
Keywords: python,first package
Platform: UNKNOWN
Classifier: Development Status :: 3 - Alpha
Classifier: Intended Audience :: Education
Classifier: Programming Language :: Python :: 3
Classifier: Operating System :: Microsoft :: Windows
